campa/__init__.py
campa/campa.ini.example
campa/constants.py
campa/utils.py
campa/cli/main.py
campa/cli/prepare_config.py
campa/data/__init__.py
campa/data/_conditions.py
campa/data/_data.py
campa/data/_download_data.py
campa/data/_img_utils.py
campa/data/_nn_dataset.py
campa/pl/__init__.py
campa/pl/_intensity_features.py
campa/pl/_object_features.py
campa/pl/_plot.py
campa/pl/_spatial_features.py
campa/tl/__init__.py
campa/tl/_cluster.py
campa/tl/_estimator.py
campa/tl/_evaluate.py
campa/tl/_experiment.py
campa/tl/_features.py
campa/tl/_layers.py
campa/tl/_losses.py
campa/tl/_models.py
tests/__init__.py
tests/conftest.py
tests/helpers.py
tests/test_save_load_experiment.py
tests/test_subsample.py
tests/test_subset.py
tests/test_workflow.py
campa-1.1.0.dist-info/LICENSE
campa-1.1.0.dist-info/METADATA
campa-1.1.0.dist-info/WHEEL
campa-1.1.0.dist-info/entry_points.txt
campa-1.1.0.dist-info/top_level.txt
campa-1.1.0.dist-info/RECORD
