Metadata-Version: 2.1
Name: campa
Version: 1.1.0
Home-page: https://github.com/theislab/campa
Download-URL: https://pypi.org/project/campa/
Author: Hannah Spitzer, Scott Berry
Author-email: hannah.spitzer@helmholtz-muenchen.de, scott.berry@unsw.edu.au
Maintainer: Hannah Spitzer, Scott Berry
Maintainer-email: hannah.spitzer@helmholtz-muenchen.de, scott.berry@unsw.edu.au
License: BSD
Project-URL: Documentation, https://campa.readthedocs.io/en/stable
Project-URL: Source Code, https://github.com/theislab/campa
Keywords: bio-informatics,image analysis,multiplexed imaging,single-cell,spatial data analysis,subcellular landmarks
Platform: Linux
Platform: MacOSX
Classifier: Development Status :: 5 - Production/Stable
Classifier: Intended Audience :: Science/Research
Classifier: Natural Language :: English
Classifier: License :: OSI Approved :: BSD License
Classifier: Operating System :: POSIX :: Linux
Classifier: Operating System :: MacOS :: MacOS X
Classifier: Typing :: Typed
Classifier: Programming Language :: Python :: 3
Classifier: Programming Language :: Python :: 3.9
Classifier: Environment :: Console
Classifier: Framework :: Jupyter
Classifier: Intended Audience :: Science/Research
Classifier: Topic :: Scientific/Engineering :: Bio-Informatics
License-File: LICENSE
Requires-Dist: numba
Requires-Dist: pandas (>=1.2.0)
Requires-Dist: scanpy[leiden] (>=1.8.0)
Requires-Dist: scikit-learn
Requires-Dist: squidpy
Requires-Dist: tensorflow (<2.11,>=2.6)
Requires-Dist: tqdm (>=4.50.2)
Provides-Extra: dev
Requires-Dist: pre-commit (>=2.9.0) ; extra == 'dev'
Provides-Extra: docs
Requires-Dist: ipykernel ; extra == 'docs'
Requires-Dist: jinja2 (==3.0.3) ; extra == 'docs'
Requires-Dist: nbsphinx (>=0.8.1) ; extra == 'docs'
Requires-Dist: pypandoc ; extra == 'docs'
Requires-Dist: sphinx (>=4) ; extra == 'docs'
Requires-Dist: sphinx-argparse ; extra == 'docs'
Requires-Dist: sphinx-autodoc-typehints (>=1.10.3) ; extra == 'docs'
Requires-Dist: sphinx-rtd-theme ; extra == 'docs'
Requires-Dist: sphinxcontrib-spelling ; extra == 'docs'
Provides-Extra: test
Requires-Dist: tox (>=3.20.1) ; extra == 'test'
Requires-Dist: pytest ; extra == 'test'
Requires-Dist: pytest-cov ; extra == 'test'
Requires-Dist: pytest-dependency ; extra == 'test'
